ismgcc/__init__.py
ismgcc/finder.py
ismgcc/post.py
ismgcc/utils.py
ismgcc-0.1.2.dist-info/METADATA
ismgcc-0.1.2.dist-info/WHEEL
ismgcc-0.1.2.dist-info/licenses/LICENSE
ismgcc-0.1.2.dist-info/RECORD
