Metadata-Version: 2.3
Name: ismgcc
Version: 0.1.2
Summary: Finding velocity coherent structures in molecular ISM using Gaussian decomposition and Graph theory
Project-URL: Homepage, https://github.com/Haoran-Feng/ismgcc
Project-URL: Issues, https://github.com/Haoran-Feng/ismgcc/issues
Author-email: Haoran Feng <hrfeng@pmo.ac.cn>
License-File: LICENSE
Classifier: License :: OSI Approved :: MIT License
Classifier: Operating System :: OS Independent
Classifier: Programming Language :: Python :: 3
Requires-Python: >=3.8
Requires-Dist: astropy
Requires-Dist: joblib
Requires-Dist: matplotlib
Requires-Dist: networkx>=3.2
Requires-Dist: numpy
Requires-Dist: pandas
Requires-Dist: pyarrow
Requires-Dist: regions
Requires-Dist: scikit-image
Requires-Dist: scikit-learn
Requires-Dist: scipy
Requires-Dist: spectral-cube
Requires-Dist: tqdm
